{"title": "GBL", "id": "tg-4923007431547551745", "net.maunium.telegram.pack": {"short_name": "gblpack", "hash": "-869472689"}, "stickers": [{"body": "😳", "url": "mxc://matrix.org/uXXMqOlzMWZCRBUrzQDCEGps", "info": {"w": 124, "h": 256, "size": 151773, "mimetype": "image/png", "thumbnail_url": "mxc://matrix.org/uXXMqOlzMWZCRBUrzQDCEGps", "thumbnail_info": {"w": 124, "h": 256, "size": 151773, "mimetype": "image/png"}}, "msgtype": "m.sticker", "id": "tg-6271458396046623457", "net.maunium.telegram.sticker": {"pack": {"id": "4923007431547551745", "short_name": "gblpack"}, "id": "6271458396046623457", "emoticons": ["😳"]}}, {"body": "👍", "url": "mxc://matrix.org/oMEToAGiJcSitAeEziuCSCrV", "info": {"w": 256, "h": 190, "size": 213386, "mimetype": "image/png", "thumbnail_url": "mxc://matrix.org/oMEToAGiJcSitAeEziuCSCrV", "thumbnail_info": {"w": 256, "h": 190, "size": 213386, "mimetype": "image/png"}}, "msgtype": "m.sticker", "id": "tg-6271648014557774063", "net.maunium.telegram.sticker": {"pack": {"id": "4923007431547551745", "short_name": "gblpack"}, "id": "6271648014557774063", "emoticons": ["👍"]}}, {"body": "😳", "url": "mxc://matrix.org/pXchXbYjmhIKfNvzeIikzsQo", "info": {"w": 256, "h": 230, "size": 293841, "mimetype": "image/png", "thumbnail_url": "mxc://matrix.org/pXchXbYjmhIKfNvzeIikzsQo", "thumbnail_info": {"w": 256, "h": 230, "size": 293841, "mimetype": "image/png"}}, "msgtype": "m.sticker", "id": "tg-6273916315635810467", "net.maunium.telegram.sticker": {"pack": {"id": "4923007431547551745", "short_name": "gblpack"}, "id": "6273916315635810467", "emoticons": ["😳"]}}, {"body": "😌", "url": "mxc://matrix.org/OoRwpwUwKojlkSivYIZGkDGv", "info": {"w": 256, "h": 143, "size": 128150, "mimetype": "image/png", "thumbnail_url": "mxc://matrix.org/OoRwpwUwKojlkSivYIZGkDGv", "thumbnail_info": {"w": 256, "h": 143, "size": 128150, "mimetype": "image/png"}}, "msgtype": "m.sticker", "id": "tg-6271502264842584227", "net.maunium.telegram.sticker": {"pack": {"id": "4923007431547551745", "short_name": "gblpack"}, "id": "6271502264842584227", "emoticons": ["😌"]}}, {"body": "😳", "url": "mxc://matrix.org/lsnXlGnVjtwWBSriuLIErHNk", "info": {"w": 241, "h": 256, "size": 294569, "mimetype": "image/png", "thumbnail_url": "mxc://matrix.org/lsnXlGnVjtwWBSriuLIErHNk", "thumbnail_info": {"w": 241, "h": 256, "size": 294569, "mimetype": "image/png"}}, "msgtype": "m.sticker", "id": "tg-6278019899189100786", "net.maunium.telegram.sticker": {"pack": {"id": "4923007431547551745", "short_name": "gblpack"}, "id": "6278019899189100786", "emoticons": ["😳"]}}, {"body": "😚", "url": "mxc://matrix.org/ItLnNduaTSZfeBmgdfbXDiCb", "info": {"w": 256, "h": 156, "size": 127262, "mimetype": "image/png", "thumbnail_url": "mxc://matrix.org/ItLnNduaTSZfeBmgdfbXDiCb", "thumbnail_info": {"w": 256, "h": 156, "size": 127262, "mimetype": "image/png"}}, "msgtype": "m.sticker", "id": "tg-6280398409127952581", "net.maunium.telegram.sticker": {"pack": {"id": "4923007431547551745", "short_name": "gblpack"}, "id": "6280398409127952581", "emoticons": ["😚"]}}, {"body": "🤔", "url": "mxc://matrix.org/MgInmxCIxoqBzzmECCgljxGc", "info": {"w": 256, "h": 242, "size": 283051, "mimetype": "image/png", "thumbnail_url": "mxc://matrix.org/MgInmxCIxoqBzzmECCgljxGc", "thumbnail_info": {"w": 256, "h": 242, "size": 283051, "mimetype": "image/png"}}, "msgtype": "m.sticker", "id": "tg-6174700870291161323", "net.maunium.telegram.sticker": {"pack": {"id": "4923007431547551745", "short_name": "gblpack"}, "id": "6174700870291161323", "emoticons": ["🤔"]}}, {"body": "🤨", "url": "mxc://matrix.org/IKfQUutXHqpHUpoZBpVTaOlf", "info": {"w": 256, "h": 138, "size": 99695, "mimetype": "image/png", "thumbnail_url": "mxc://matrix.org/IKfQUutXHqpHUpoZBpVTaOlf", "thumbnail_info": {"w": 256, "h": 138, "size": 99695, "mimetype": "image/png"}}, "msgtype": "m.sticker", "id": "tg-6177008088067866922", "net.maunium.telegram.sticker": {"pack": {"id": "4923007431547551745", "short_name": "gblpack"}, "id": "6177008088067866922", "emoticons": ["🤨"]}}, {"body": "🙃", "url": "mxc://matrix.org/BfkKCtcbjWYCFkWPtSpISwWA", "info": {"w": 256, "h": 202, "size": 180759, "mimetype": "image/png", "thumbnail_url": "mxc://matrix.org/BfkKCtcbjWYCFkWPtSpISwWA", "thumbnail_info": {"w": 256, "h": 202, "size": 180759, "mimetype": "image/png"}}, "msgtype": "m.sticker", "id": "tg-6176951798226485608", "net.maunium.telegram.sticker": {"pack": {"id": "4923007431547551745", "short_name": "gblpack"}, "id": "6176951798226485608", "emoticons": ["🙃"]}}, {"body": "😙", "url": "mxc://matrix.org/NvrSSQbGuPTNPNyBVsRYnmbL", "info": {"w": 256, "h": 128, "size": 131782, "mimetype": "image/png", "thumbnail_url": "mxc://matrix.org/NvrSSQbGuPTNPNyBVsRYnmbL", "thumbnail_info": {"w": 256, "h": 128, "size": 131782, "mimetype": "image/png"}}, "msgtype": "m.sticker", "id": "tg-6176942293463859393", "net.maunium.telegram.sticker": {"pack": {"id": "4923007431547551745", "short_name": "gblpack"}, "id": "6176942293463859393", "emoticons": ["😙"]}}, {"body": "🤪", "url": "mxc://matrix.org/eHYpAmjgrXICFQLSoVwOKlQf", "info": {"w": 256, "h": 255, "size": 271189, "mimetype": "image/png", "thumbnail_url": "mxc://matrix.org/eHYpAmjgrXICFQLSoVwOKlQf", "thumbnail_info": {"w": 256, "h": 255, "size": 271189, "mimetype": "image/png"}}, "msgtype": "m.sticker", "id": "tg-6177092986686406850", "net.maunium.telegram.sticker": {"pack": {"id": "4923007431547551745", "short_name": "gblpack"}, "id": "6177092986686406850", "emoticons": ["🤪"]}}, {"body": "🤔", "url": "mxc://matrix.org/tgJZZLaezlJFqeWvWfHqyOIQ", "info": {"w": 248, "h": 256, "size": 278599, "mimetype": "image/png", "thumbnail_url": "mxc://matrix.org/tgJZZLaezlJFqeWvWfHqyOIQ", "thumbnail_info": {"w": 248, "h": 256, "size": 278599, "mimetype": "image/png"}}, "msgtype": "m.sticker", "id": "tg-6177184379295498674", "net.maunium.telegram.sticker": {"pack": {"id": "4923007431547551745", "short_name": "gblpack"}, "id": "6177184379295498674", "emoticons": ["🤔"]}}, {"body": "😊", "url": "mxc://matrix.org/wUhBrammXWfJBiyKSTdSmsnu", "info": {"w": 220, "h": 256, "size": 238295, "mimetype": "image/png", "thumbnail_url": "mxc://matrix.org/wUhBrammXWfJBiyKSTdSmsnu", "thumbnail_info": {"w": 220, "h": 256, "size": 238295, "mimetype": "image/png"}}, "msgtype": "m.sticker", "id": "tg-6176997531038253269", "net.maunium.telegram.sticker": {"pack": {"id": "4923007431547551745", "short_name": "gblpack"}, "id": "6176997531038253269", "emoticons": ["😊"]}}, {"body": "😣", "url": "mxc://matrix.org/eCMopHhylCGTtugUYjaMTzHx", "info": {"w": 256, "h": 254, "size": 247291, "mimetype": "image/png", "thumbnail_url": "mxc://matrix.org/eCMopHhylCGTtugUYjaMTzHx", "thumbnail_info": {"w": 256, "h": 254, "size": 247291, "mimetype": "image/png"}}, "msgtype": "m.sticker", "id": "tg-6176729117057089796", "net.maunium.telegram.sticker": {"pack": {"id": "4923007431547551745", "short_name": "gblpack"}, "id": "6176729117057089796", "emoticons": ["😣"]}}, {"body": "😙", "url": "mxc://matrix.org/RtsPUTPCyTkJbVIXFuXPeMhK", "info": {"w": 256, "h": 207, "size": 248086, "mimetype": "image/png", "thumbnail_url": "mxc://matrix.org/RtsPUTPCyTkJbVIXFuXPeMhK", "thumbnail_info": {"w": 256, "h": 207, "size": 248086, "mimetype": "image/png"}}, "msgtype": "m.sticker", "id": "tg-6174819132215656768", "net.maunium.telegram.sticker": {"pack": {"id": "4923007431547551745", "short_name": "gblpack"}, "id": "6174819132215656768", "emoticons": ["😙"]}}, {"body": "🔪", "url": "mxc://matrix.org/ejtoMQppHHdOixnRAkpwcRbJ", "info": {"w": 256, "h": 256, "size": 285260, "mimetype": "image/png", "thumbnail_url": "mxc://matrix.org/ejtoMQppHHdOixnRAkpwcRbJ", "thumbnail_info": {"w": 256, "h": 256, "size": 285260, "mimetype": "image/png"}}, "msgtype": "m.sticker", "id": "tg-6176836053152825759", "net.maunium.telegram.sticker": {"pack": {"id": "4923007431547551745", "short_name": "gblpack"}, "id": "6176836053152825759", "emoticons": ["🔪"]}}, {"body": "🤨", "url": "mxc://matrix.org/XCINsbXxKZkiBUwEfCxECdwm", "info": {"w": 154, "h": 256, "size": 150426, "mimetype": "image/png", "thumbnail_url": "mxc://matrix.org/XCINsbXxKZkiBUwEfCxECdwm", "thumbnail_info": {"w": 154, "h": 256, "size": 150426, "mimetype": "image/png"}}, "msgtype": "m.sticker", "id": "tg-6174439495761396201", "net.maunium.telegram.sticker": {"pack": {"id": "4923007431547551745", "short_name": "gblpack"}, "id": "6174439495761396201", "emoticons": ["🤨"]}}, {"body": "👍", "url": "mxc://matrix.org/ttmetcprlPYXywrEoFcTHxAs", "info": {"w": 234, "h": 256, "size": 230521, "mimetype": "image/png", "thumbnail_url": "mxc://matrix.org/ttmetcprlPYXywrEoFcTHxAs", "thumbnail_info": {"w": 234, "h": 256, "size": 230521, "mimetype": "image/png"}}, "msgtype": "m.sticker", "id": "tg-6177084920737825014", "net.maunium.telegram.sticker": {"pack": {"id": "4923007431547551745", "short_name": "gblpack"}, "id": "6177084920737825014", "emoticons": ["👍"]}}, {"body": "🤨", "url": "mxc://matrix.org/mXYThQwIqZxoKWptmAjdxsoH", "info": {"w": 256, "h": 235, "size": 219526, "mimetype": "image/png", "thumbnail_url": "mxc://matrix.org/mXYThQwIqZxoKWptmAjdxsoH", "thumbnail_info": {"w": 256, "h": 235, "size": 219526, "mimetype": "image/png"}}, "msgtype": "m.sticker", "id": "tg-6174604083203146078", "net.maunium.telegram.sticker": {"pack": {"id": "4923007431547551745", "short_name": "gblpack"}, "id": "6174604083203146078", "emoticons": ["🤨"]}}, {"body": "😭", "url": "mxc://matrix.org/zHXgIQdPnmZpZtqCwLYGPkwM", "info": {"w": 256, "h": 256, "size": 373206, "mimetype": "image/png", "thumbnail_url": "mxc://matrix.org/zHXgIQdPnmZpZtqCwLYGPkwM", "thumbnail_info": {"w": 256, "h": 256, "size": 373206, "mimetype": "image/png"}}, "msgtype": "m.sticker", "id": "tg-6176888048026910963", "net.maunium.telegram.sticker": {"pack": {"id": "4923007431547551745", "short_name": "gblpack"}, "id": "6176888048026910963", "emoticons": ["😭", "🎧"]}}, {"body": "😨", "url": "mxc://matrix.org/UsHfxYOCxRjIpBeayQIGihcP", "info": {"w": 256, "h": 256, "size": 394669, "mimetype": "image/png", "thumbnail_url": "mxc://matrix.org/UsHfxYOCxRjIpBeayQIGihcP", "thumbnail_info": {"w": 256, "h": 256, "size": 394669, "mimetype": "image/png"}}, "msgtype": "m.sticker", "id": "tg-6177085058176778498", "net.maunium.telegram.sticker": {"pack": {"id": "4923007431547551745", "short_name": "gblpack"}, "id": "6177085058176778498", "emoticons": ["😨"]}}, {"body": "🤔", "url": "mxc://matrix.org/punvDRrwUhyUSMMDcvLIQsoK", "info": {"w": 232, "h": 256, "size": 199777, "mimetype": "image/png", "thumbnail_url": "mxc://matrix.org/punvDRrwUhyUSMMDcvLIQsoK", "thumbnail_info": {"w": 232, "h": 256, "size": 199777, "mimetype": "image/png"}}, "msgtype": "m.sticker", "id": "tg-6177070008611373330", "net.maunium.telegram.sticker": {"pack": {"id": "4923007431547551745", "short_name": "gblpack"}, "id": "6177070008611373330", "emoticons": ["🤔"]}}, {"body": "😊", "url": "mxc://matrix.org/TOnsUNNYtxcukDWntPEdPkld", "info": {"w": 135, "h": 256, "size": 173760, "mimetype": "image/png", "thumbnail_url": "mxc://matrix.org/TOnsUNNYtxcukDWntPEdPkld", "thumbnail_info": {"w": 135, "h": 256, "size": 173760, "mimetype": "image/png"}}, "msgtype": "m.sticker", "id": "tg-6174830586893435152", "net.maunium.telegram.sticker": {"pack": {"id": "4923007431547551745", "short_name": "gblpack"}, "id": "6174830586893435152", "emoticons": ["😊"]}}, {"body": "🤔", "url": "mxc://matrix.org/JpkhKzxNjEKpErizNPIFQacM", "info": {"w": 240, "h": 256, "size": 287648, "mimetype": "image/png", "thumbnail_url": "mxc://matrix.org/JpkhKzxNjEKpErizNPIFQacM", "thumbnail_info": {"w": 240, "h": 256, "size": 287648, "mimetype": "image/png"}}, "msgtype": "m.sticker", "id": "tg-6174532477508387031", "net.maunium.telegram.sticker": {"pack": {"id": "4923007431547551745", "short_name": "gblpack"}, "id": "6174532477508387031", "emoticons": ["🤔"]}}, {"body": "🤨", "url": "mxc://matrix.org/TRnlJRFYtMNkBKLwlOudaoaP", "info": {"w": 256, "h": 144, "size": 189964, "mimetype": "image/png", "thumbnail_url": "mxc://matrix.org/TRnlJRFYtMNkBKLwlOudaoaP", "thumbnail_info": {"w": 256, "h": 144, "size": 189964, "mimetype": "image/png"}}, "msgtype": "m.sticker", "id": "tg-6176738488675729672", "net.maunium.telegram.sticker": {"pack": {"id": "4923007431547551745", "short_name": "gblpack"}, "id": "6176738488675729672", "emoticons": ["🤨"]}}, {"body": "☹️", "url": "mxc://matrix.org/KYwRcwntQqQeUwIakyStFlpN", "info": {"w": 256, "h": 211, "size": 125281, "mimetype": "image/png", "thumbnail_url": "mxc://matrix.org/KYwRcwntQqQeUwIakyStFlpN", "thumbnail_info": {"w": 256, "h": 211, "size": 125281, "mimetype": "image/png"}}, "msgtype": "m.sticker", "id": "tg-6174900852558397786", "net.maunium.telegram.sticker": {"pack": {"id": "4923007431547551745", "short_name": "gblpack"}, "id": "6174900852558397786", "emoticons": ["☹"]}}, {"body": "🤨", "url": "mxc://matrix.org/BszJjIhNAUJmSrJCpdgAfLze", "info": {"w": 256, "h": 224, "size": 260758, "mimetype": "image/png", "thumbnail_url": "mxc://matrix.org/BszJjIhNAUJmSrJCpdgAfLze", "thumbnail_info": {"w": 256, "h": 224, "size": 260758, "mimetype": "image/png"}}, "msgtype": "m.sticker", "id": "tg-6176942615586406653", "net.maunium.telegram.sticker": {"pack": {"id": "4923007431547551745", "short_name": "gblpack"}, "id": "6176942615586406653", "emoticons": ["🤨"]}}, {"body": "🤪", "url": "mxc://matrix.org/KmrHWsjnfsrOQWqOVnsvaQaN", "info": {"w": 252, "h": 256, "size": 266350, "mimetype": "image/png", "thumbnail_url": "mxc://matrix.org/KmrHWsjnfsrOQWqOVnsvaQaN", "thumbnail_info": {"w": 252, "h": 256, "size": 266350, "mimetype": "image/png"}}, "msgtype": "m.sticker", "id": "tg-6176699997178822861", "net.maunium.telegram.sticker": {"pack": {"id": "4923007431547551745", "short_name": "gblpack"}, "id": "6176699997178822861", "emoticons": ["🤪"]}}, {"body": "🤨", "url": "mxc://matrix.org/NLkvQXNgamlOXpUioMlBvSSk", "info": {"w": 223, "h": 256, "size": 298642, "mimetype": "image/png", "thumbnail_url": "mxc://matrix.org/NLkvQXNgamlOXpUioMlBvSSk", "thumbnail_info": {"w": 223, "h": 256, "size": 298642, "mimetype": "image/png"}}, "msgtype": "m.sticker", "id": "tg-6177230837956739340", "net.maunium.telegram.sticker": {"pack": {"id": "4923007431547551745", "short_name": "gblpack"}, "id": "6177230837956739340", "emoticons": ["🤨"]}}, {"body": "😣", "url": "mxc://matrix.org/tuDJhQzXRHlRsOEkPtgkhyAv", "info": {"w": 256, "h": 255, "size": 278781, "mimetype": "image/png", "thumbnail_url": "mxc://matrix.org/tuDJhQzXRHlRsOEkPtgkhyAv", "thumbnail_info": {"w": 256, "h": 255, "size": 278781, "mimetype": "image/png"}}, "msgtype": "m.sticker", "id": "tg-6177211935805669625", "net.maunium.telegram.sticker": {"pack": {"id": "4923007431547551745", "short_name": "gblpack"}, "id": "6177211935805669625", "emoticons": ["😣"]}}, {"body": "🙃", "url": "mxc://matrix.org/KvBvYnkIlVzdEmugtTcTHneD", "info": {"w": 186, "h": 256, "size": 115842, "mimetype": "image/png", "thumbnail_url": "mxc://matrix.org/KvBvYnkIlVzdEmugtTcTHneD", "thumbnail_info": {"w": 186, "h": 256, "size": 115842, "mimetype": "image/png"}}, "msgtype": "m.sticker", "id": "tg-6176999519608111537", "net.maunium.telegram.sticker": {"pack": {"id": "4923007431547551745", "short_name": "gblpack"}, "id": "6176999519608111537", "emoticons": ["🙃"]}}, {"body": "🤨", "url": "mxc://matrix.org/otTqiTUQtOyPserFWDIuWbUA", "info": {"w": 256, "h": 242, "size": 314755, "mimetype": "image/png", "thumbnail_url": "mxc://matrix.org/otTqiTUQtOyPserFWDIuWbUA", "thumbnail_info": {"w": 256, "h": 242, "size": 314755, "mimetype": "image/png"}}, "msgtype": "m.sticker", "id": "tg-6176917670416351557", "net.maunium.telegram.sticker": {"pack": {"id": "4923007431547551745", "short_name": "gblpack"}, "id": "6176917670416351557", "emoticons": ["🤨"]}}, {"body": "🚀", "url": "mxc://matrix.org/LpNfZFaXmqblZJqJXuuaXMBZ", "info": {"w": 256, "h": 142, "size": 183401, "mimetype": "image/png", "thumbnail_url": "mxc://matrix.org/LpNfZFaXmqblZJqJXuuaXMBZ", "thumbnail_info": {"w": 256, "h": 142, "size": 183401, "mimetype": "image/png"}}, "msgtype": "m.sticker", "id": "tg-6176863313310253335", "net.maunium.telegram.sticker": {"pack": {"id": "4923007431547551745", "short_name": "gblpack"}, "id": "6176863313310253335", "emoticons": ["🚀"]}}, {"body": "🤨", "url": "mxc://matrix.org/PcffODMTytZkfCKosFlUIiWs", "info": {"w": 256, "h": 232, "size": 211113, "mimetype": "image/png", "thumbnail_url": "mxc://matrix.org/PcffODMTytZkfCKosFlUIiWs", "thumbnail_info": {"w": 256, "h": 232, "size": 211113, "mimetype": "image/png"}}, "msgtype": "m.sticker", "id": "tg-6176751747239772455", "net.maunium.telegram.sticker": {"pack": {"id": "4923007431547551745", "short_name": "gblpack"}, "id": "6176751747239772455", "emoticons": ["🤨"]}}, {"body": "👍", "url": "mxc://matrix.org/slWmEuygSHnQMNLIGZludoQD", "info": {"w": 256, "h": 228, "size": 240574, "mimetype": "image/png", "thumbnail_url": "mxc://matrix.org/slWmEuygSHnQMNLIGZludoQD", "thumbnail_info": {"w": 256, "h": 228, "size": 240574, "mimetype": "image/png"}}, "msgtype": "m.sticker", "id": "tg-6177217922990080210", "net.maunium.telegram.sticker": {"pack": {"id": "4923007431547551745", "short_name": "gblpack"}, "id": "6177217922990080210", "emoticons": ["👍", "🐼"]}}, {"body": "🧐", "url": "mxc://matrix.org/OmPatosYrgoeqOOneuPqPMIv", "info": {"w": 256, "h": 250, "size": 221091, "mimetype": "image/png", "thumbnail_url": "mxc://matrix.org/OmPatosYrgoeqOOneuPqPMIv", "thumbnail_info": {"w": 256, "h": 250, "size": 221091, "mimetype": "image/png"}}, "msgtype": "m.sticker", "id": "tg-6177199308601819411", "net.maunium.telegram.sticker": {"pack": {"id": "4923007431547551745", "short_name": "gblpack"}, "id": "6177199308601819411", "emoticons": ["🧐"]}}, {"body": "🤨", "url": "mxc://matrix.org/wdojizLWGEqZszDqLpnkKVfh", "info": {"w": 256, "h": 164, "size": 165784, "mimetype": "image/png", "thumbnail_url": "mxc://matrix.org/wdojizLWGEqZszDqLpnkKVfh", "thumbnail_info": {"w": 256, "h": 164, "size": 165784, "mimetype": "image/png"}}, "msgtype": "m.sticker", "id": "tg-6192768517805179176", "net.maunium.telegram.sticker": {"pack": {"id": "4923007431547551745", "short_name": "gblpack"}, "id": "6192768517805179176", "emoticons": ["🤨"]}}, {"body": "😅", "url": "mxc://matrix.org/znHQDdaDJsaNUQYtOFYDxmxA", "info": {"w": 256, "h": 192, "size": 219784, "mimetype": "image/png", "thumbnail_url": "mxc://matrix.org/znHQDdaDJsaNUQYtOFYDxmxA", "thumbnail_info": {"w": 256, "h": 192, "size": 219784, "mimetype": "image/png"}}, "msgtype": "m.sticker", "id": "tg-6194841071453733136", "net.maunium.telegram.sticker": {"pack": {"id": "4923007431547551745", "short_name": "gblpack"}, "id": "6194841071453733136", "emoticons": ["😅"]}}, {"body": "💀", "url": "mxc://matrix.org/naWDrrGUEjvIlDcBTrCyasYu", "info": {"w": 256, "h": 256, "size": 350797, "mimetype": "image/png", "thumbnail_url": "mxc://matrix.org/naWDrrGUEjvIlDcBTrCyasYu", "thumbnail_info": {"w": 256, "h": 256, "size": 350797, "mimetype": "image/png"}}, "msgtype": "m.sticker", "id": "tg-6195165036541903044", "net.maunium.telegram.sticker": {"pack": {"id": "4923007431547551745", "short_name": "gblpack"}, "id": "6195165036541903044", "emoticons": ["💀"]}}, {"body": "👮", "url": "mxc://matrix.org/gRPIMxOKVqsdQXYEYxFhaVXx", "info": {"w": 254, "h": 256, "size": 373809, "mimetype": "image/png", "thumbnail_url": "mxc://matrix.org/gRPIMxOKVqsdQXYEYxFhaVXx", "thumbnail_info": {"w": 254, "h": 256, "size": 373809, "mimetype": "image/png"}}, "msgtype": "m.sticker", "id": "tg-6195255308164530392", "net.maunium.telegram.sticker": {"pack": {"id": "4923007431547551745", "short_name": "gblpack"}, "id": "6195255308164530392", "emoticons": ["👮"]}}, {"body": "😭", "url": "mxc://matrix.org/RxgjlPhrmjBRLQlFPbinNNln", "info": {"w": 245, "h": 256, "size": 282844, "mimetype": "image/png", "thumbnail_url": "mxc://matrix.org/RxgjlPhrmjBRLQlFPbinNNln", "thumbnail_info": {"w": 245, "h": 256, "size": 282844, "mimetype": "image/png"}}, "msgtype": "m.sticker", "id": "tg-6192614109435920609", "net.maunium.telegram.sticker": {"pack": {"id": "4923007431547551745", "short_name": "gblpack"}, "id": "6192614109435920609", "emoticons": ["😭"]}}, {"body": "🤔", "url": "mxc://matrix.org/qrBMXSawcOaILeXLZSAfRBpI", "info": {"w": 177, "h": 256, "size": 253584, "mimetype": "image/png", "thumbnail_url": "mxc://matrix.org/qrBMXSawcOaILeXLZSAfRBpI", "thumbnail_info": {"w": 177, "h": 256, "size": 253584, "mimetype": "image/png"}}, "msgtype": "m.sticker", "id": "tg-6194892520866971838", "net.maunium.telegram.sticker": {"pack": {"id": "4923007431547551745", "short_name": "gblpack"}, "id": "6194892520866971838", "emoticons": ["🤔"]}}, {"body": "👍", "url": "mxc://matrix.org/REKAKsvTWnSoDjRuUygImpad", "info": {"w": 256, "h": 180, "size": 206077, "mimetype": "image/png", "thumbnail_url": "mxc://matrix.org/REKAKsvTWnSoDjRuUygImpad", "thumbnail_info": {"w": 256, "h": 180, "size": 206077, "mimetype": "image/png"}}, "msgtype": "m.sticker", "id": "tg-6217301559978492219", "net.maunium.telegram.sticker": {"pack": {"id": "4923007431547551745", "short_name": "gblpack"}, "id": "6217301559978492219", "emoticons": ["👍"]}}, {"body": "🤨", "url": "mxc://matrix.org/sAGJPvrxQbueOaHgOweoxTAJ", "info": {"w": 256, "h": 256, "size": 233249, "mimetype": "image/png", "thumbnail_url": "mxc://matrix.org/sAGJPvrxQbueOaHgOweoxTAJ", "thumbnail_info": {"w": 256, "h": 256, "size": 233249, "mimetype": "image/png"}}, "msgtype": "m.sticker", "id": "tg-6242260972145213687", "net.maunium.telegram.sticker": {"pack": {"id": "4923007431547551745", "short_name": "gblpack"}, "id": "6242260972145213687", "emoticons": ["🤨"]}}, {"body": "🤪", "url": "mxc://matrix.org/ODEGAjfUZBNmODQVzlZgrKpB", "info": {"w": 256, "h": 256, "size": 444256, "mimetype": "image/png", "thumbnail_url": "mxc://matrix.org/ODEGAjfUZBNmODQVzlZgrKpB", "thumbnail_info": {"w": 256, "h": 256, "size": 444256, "mimetype": "image/png"}}, "msgtype": "m.sticker", "id": "tg-6242376210412732743", "net.maunium.telegram.sticker": {"pack": {"id": "4923007431547551745", "short_name": "gblpack"}, "id": "6242376210412732743", "emoticons": ["🤪"]}}, {"body": "☹️", "url": "mxc://matrix.org/rWprXOEhvmgLJFCxKdZYDVwr", "info": {"w": 256, "h": 213, "size": 554409, "mimetype": "image/png", "thumbnail_url": "mxc://matrix.org/rWprXOEhvmgLJFCxKdZYDVwr", "thumbnail_info": {"w": 256, "h": 213, "size": 554409, "mimetype": "image/png"}}, "msgtype": "m.sticker", "id": "tg-6266958657594851771", "net.maunium.telegram.sticker": {"pack": {"id": "4923007431547551745", "short_name": "gblpack"}, "id": "6266958657594851771", "emoticons": ["☹"]}}, {"body": "🙃", "url": "mxc://matrix.org/YtwvdRVvytgAVsKqXTQPYMQV", "info": {"w": 256, "h": 221, "size": 210688, "mimetype": "image/png", "thumbnail_url": "mxc://matrix.org/YtwvdRVvytgAVsKqXTQPYMQV", "thumbnail_info": {"w": 256, "h": 221, "size": 210688, "mimetype": "image/png"}}, "msgtype": "m.sticker", "id": "tg-6282960589048250684", "net.maunium.telegram.sticker": {"pack": {"id": "4923007431547551745", "short_name": "gblpack"}, "id": "6282960589048250684", "emoticons": ["🙃"]}}, {"body": "😝", "url": "mxc://matrix.org/pmGwhfMdewojlUJzBwBiqCfE", "info": {"w": 201, "h": 256, "size": 229942, "mimetype": "image/png", "thumbnail_url": "mxc://matrix.org/pmGwhfMdewojlUJzBwBiqCfE", "thumbnail_info": {"w": 201, "h": 256, "size": 229942, "mimetype": "image/png"}}, "msgtype": "m.sticker", "id": "tg-6296122593636254039", "net.maunium.telegram.sticker": {"pack": {"id": "4923007431547551745", "short_name": "gblpack"}, "id": "6296122593636254039", "emoticons": ["😝"]}}, {"body": "🤔", "url": "mxc://matrix.org/xTqbVfXivzvEfrYHXtImejKH", "info": {"w": 221, "h": 256, "size": 225643, "mimetype": "image/png", "thumbnail_url": "mxc://matrix.org/xTqbVfXivzvEfrYHXtImejKH", "thumbnail_info": {"w": 221, "h": 256, "size": 225643, "mimetype": "image/png"}}, "msgtype": "m.sticker", "id": "tg-6293939861191655776", "net.maunium.telegram.sticker": {"pack": {"id": "4923007431547551745", "short_name": "gblpack"}, "id": "6293939861191655776", "emoticons": ["🤔"]}}, {"body": "😁", "url": "mxc://matrix.org/IyHkdPVWGEkxCsnhQzbKLrlY", "info": {"w": 177, "h": 256, "size": 190177, "mimetype": "image/png", "thumbnail_url": "mxc://matrix.org/IyHkdPVWGEkxCsnhQzbKLrlY", "thumbnail_info": {"w": 177, "h": 256, "size": 190177, "mimetype": "image/png"}}, "msgtype": "m.sticker", "id": "tg-6296578431400280336", "net.maunium.telegram.sticker": {"pack": {"id": "4923007431547551745", "short_name": "gblpack"}, "id": "6296578431400280336", "emoticons": ["😁"]}}, {"body": "🙂", "url": "mxc://matrix.org/GvjfQiNEDfSWbEQLozKpRvWK", "info": {"w": 246, "h": 256, "size": 211406, "mimetype": "image/png", "thumbnail_url": "mxc://matrix.org/GvjfQiNEDfSWbEQLozKpRvWK", "thumbnail_info": {"w": 246, "h": 256, "size": 211406, "mimetype": "image/png"}}, "msgtype": "m.sticker", "id": "tg-6161484701870588282", "net.maunium.telegram.sticker": {"pack": {"id": "4923007431547551745", "short_name": "gblpack"}, "id": "6161484701870588282", "emoticons": ["🙂"]}}, {"body": "⚡", "url": "mxc://matrix.org/EqZHIbhJAcqzvGHWtqMGjKBE", "info": {"w": 155, "h": 256, "size": 150392, "mimetype": "image/png", "thumbnail_url": "mxc://matrix.org/EqZHIbhJAcqzvGHWtqMGjKBE", "thumbnail_info": {"w": 155, "h": 256, "size": 150392, "mimetype": "image/png"}}, "msgtype": "m.sticker", "id": "tg-6194938283743511265", "net.maunium.telegram.sticker": {"pack": {"id": "4923007431547551745", "short_name": "gblpack"}, "id": "6194938283743511265", "emoticons": ["⚡"]}}, {"body": "😌", "url": "mxc://matrix.org/fBhCQWihZYaKUjQwKKwaDLla", "info": {"w": 109, "h": 256, "size": 143043, "mimetype": "image/png", "thumbnail_url": "mxc://matrix.org/fBhCQWihZYaKUjQwKKwaDLla", "thumbnail_info": {"w": 109, "h": 256, "size": 143043, "mimetype": "image/png"}}, "msgtype": "m.sticker", "id": "tg-6186138192106750374", "net.maunium.telegram.sticker": {"pack": {"id": "4923007431547551745", "short_name": "gblpack"}, "id": "6186138192106750374", "emoticons": ["👍", "😌"]}}, {"body": "🤔", "url": "mxc://matrix.org/SVzjATlRZQQCNzdLerdoRTCV", "info": {"w": 256, "h": 181, "size": 244653, "mimetype": "image/png", "thumbnail_url": "mxc://matrix.org/SVzjATlRZQQCNzdLerdoRTCV", "thumbnail_info": {"w": 256, "h": 181, "size": 244653, "mimetype": "image/png"}}, "msgtype": "m.sticker", "id": "tg-6183900428246188699", "net.maunium.telegram.sticker": {"pack": {"id": "4923007431547551745", "short_name": "gblpack"}, "id": "6183900428246188699", "emoticons": ["🤔"]}}, {"body": "😌", "url": "mxc://matrix.org/KVZyrtDgiNEdeTiGfkbbfqvm", "info": {"w": 249, "h": 256, "size": 180323, "mimetype": "image/png", "thumbnail_url": "mxc://matrix.org/KVZyrtDgiNEdeTiGfkbbfqvm", "thumbnail_info": {"w": 249, "h": 256, "size": 180323, "mimetype": "image/png"}}, "msgtype": "m.sticker", "id": "tg-6186127149745832233", "net.maunium.telegram.sticker": {"pack": {"id": "4923007431547551745", "short_name": "gblpack"}, "id": "6186127149745832233", "emoticons": ["😌"]}}, {"body": "😅", "url": "mxc://matrix.org/hfZDDAFHyQEaGBvskTujypDj", "info": {"w": 256, "h": 184, "size": 208071, "mimetype": "image/png", "thumbnail_url": "mxc://matrix.org/hfZDDAFHyQEaGBvskTujypDj", "thumbnail_info": {"w": 256, "h": 184, "size": 208071, "mimetype": "image/png"}}, "msgtype": "m.sticker", "id": "tg-6183771849810248085", "net.maunium.telegram.sticker": {"pack": {"id": "4923007431547551745", "short_name": "gblpack"}, "id": "6183771849810248085", "emoticons": ["😅"]}}, {"body": "😂", "url": "mxc://matrix.org/xQQzQgbxxHDBrsVUJBhJmGQW", "info": {"w": 256, "h": 256, "size": 262025, "mimetype": "image/png", "thumbnail_url": "mxc://matrix.org/xQQzQgbxxHDBrsVUJBhJmGQW", "thumbnail_info": {"w": 256, "h": 256, "size": 262025, "mimetype": "image/png"}}, "msgtype": "m.sticker", "id": "tg-6185939287876305594", "net.maunium.telegram.sticker": {"pack": {"id": "4923007431547551745", "short_name": "gblpack"}, "id": "6185939287876305594", "emoticons": ["😂"]}}, {"body": "🐴", "url": "mxc://matrix.org/hXLezLEUKVDPJGNluvXaMikp", "info": {"w": 212, "h": 256, "size": 160961, "mimetype": "image/png", "thumbnail_url": "mxc://matrix.org/hXLezLEUKVDPJGNluvXaMikp", "thumbnail_info": {"w": 212, "h": 256, "size": 160961, "mimetype": "image/png"}}, "msgtype": "m.sticker", "id": "tg-6186211923810320956", "net.maunium.telegram.sticker": {"pack": {"id": "4923007431547551745", "short_name": "gblpack"}, "id": "6186211923810320956", "emoticons": ["🐴"]}}, {"body": "😅", "url": "mxc://matrix.org/PMQeMyVHImHTnFSdlkoQQAQh", "info": {"w": 256, "h": 159, "size": 104989, "mimetype": "image/png", "thumbnail_url": "mxc://matrix.org/PMQeMyVHImHTnFSdlkoQQAQh", "thumbnail_info": {"w": 256, "h": 159, "size": 104989, "mimetype": "image/png"}}, "msgtype": "m.sticker", "id": "tg-6183487278162116998", "net.maunium.telegram.sticker": {"pack": {"id": "4923007431547551745", "short_name": "gblpack"}, "id": "6183487278162116998", "emoticons": ["😅"]}}, {"body": "😁", "url": "mxc://matrix.org/pQoyzardlOHeTlzTXuvpspvr", "info": {"w": 238, "h": 256, "size": 235831, "mimetype": "image/png", "thumbnail_url": "mxc://matrix.org/pQoyzardlOHeTlzTXuvpspvr", "thumbnail_info": {"w": 238, "h": 256, "size": 235831, "mimetype": "image/png"}}, "msgtype": "m.sticker", "id": "tg-6185877543426458116", "net.maunium.telegram.sticker": {"pack": {"id": "4923007431547551745", "short_name": "gblpack"}, "id": "6185877543426458116", "emoticons": ["😁"]}}, {"body": "😘", "url": "mxc://matrix.org/RBgTalznMeEgPltwjkJqwshL", "info": {"w": 229, "h": 256, "size": 329683, "mimetype": "image/png", "thumbnail_url": "mxc://matrix.org/RBgTalznMeEgPltwjkJqwshL", "thumbnail_info": {"w": 229, "h": 256, "size": 329683, "mimetype": "image/png"}}, "msgtype": "m.sticker", "id": "tg-6336753280609157492", "net.maunium.telegram.sticker": {"pack": {"id": "4923007431547551745", "short_name": "gblpack"}, "id": "6336753280609157492", "emoticons": ["😘"]}}, {"body": "😄", "url": "mxc://matrix.org/SFvRrLOXZqRSXFMqbIqVeoLa", "info": {"w": 256, "h": 145, "size": 187633, "mimetype": "image/png", "thumbnail_url": "mxc://matrix.org/SFvRrLOXZqRSXFMqbIqVeoLa", "thumbnail_info": {"w": 256, "h": 145, "size": 187633, "mimetype": "image/png"}}, "msgtype": "m.sticker", "id": "tg-6057601597737795953", "net.maunium.telegram.sticker": {"pack": {"id": "4923007431547551745", "short_name": "gblpack"}, "id": "6057601597737795953", "emoticons": ["😄"]}}, {"body": "😅", "url": "mxc://matrix.org/tdvfxSOsyaqfseTgroWYwWqc", "info": {"w": 256, "h": 209, "size": 200615, "mimetype": "image/png", "thumbnail_url": "mxc://matrix.org/tdvfxSOsyaqfseTgroWYwWqc", "thumbnail_info": {"w": 256, "h": 209, "size": 200615, "mimetype": "image/png"}}, "msgtype": "m.sticker", "id": "tg-6057642460056650345", "net.maunium.telegram.sticker": {"pack": {"id": "4923007431547551745", "short_name": "gblpack"}, "id": "6057642460056650345", "emoticons": ["😅"]}}, {"body": "😐", "url": "mxc://matrix.org/rQRgBYXCCjWHHmQLWQQKpASG", "info": {"w": 246, "h": 256, "size": 134647, "mimetype": "image/png", "thumbnail_url": "mxc://matrix.org/rQRgBYXCCjWHHmQLWQQKpASG", "thumbnail_info": {"w": 246, "h": 256, "size": 134647, "mimetype": "image/png"}}, "msgtype": "m.sticker", "id": "tg-6055620290669445575", "net.maunium.telegram.sticker": {"pack": {"id": "4923007431547551745", "short_name": "gblpack"}, "id": "6055620290669445575", "emoticons": ["😐"]}}, {"body": "😝", "url": "mxc://matrix.org/LFnNvGcvTWKWSNaHVEcyLrJg", "info": {"w": 256, "h": 237, "size": 204401, "mimetype": "image/png", "thumbnail_url": "mxc://matrix.org/LFnNvGcvTWKWSNaHVEcyLrJg", "thumbnail_info": {"w": 256, "h": 237, "size": 204401, "mimetype": "image/png"}}, "msgtype": "m.sticker", "id": "tg-6057429743211381175", "net.maunium.telegram.sticker": {"pack": {"id": "4923007431547551745", "short_name": "gblpack"}, "id": "6057429743211381175", "emoticons": ["😝"]}}, {"body": "👍", "url": "mxc://matrix.org/CvMETWwzXbawNIlCMdTnYfwQ", "info": {"w": 212, "h": 256, "size": 182850, "mimetype": "image/png", "thumbnail_url": "mxc://matrix.org/CvMETWwzXbawNIlCMdTnYfwQ", "thumbnail_info": {"w": 212, "h": 256, "size": 182850, "mimetype": "image/png"}}, "msgtype": "m.sticker", "id": "tg-6057785757345514023", "net.maunium.telegram.sticker": {"pack": {"id": "4923007431547551745", "short_name": "gblpack"}, "id": "6057785757345514023", "emoticons": ["👍"]}}, {"body": "🤔", "url": "mxc://matrix.org/SkOnWUQjcfumkJhElzCRFfki", "info": {"w": 256, "h": 245, "size": 216650, "mimetype": "image/png", "thumbnail_url": "mxc://matrix.org/SkOnWUQjcfumkJhElzCRFfki", "thumbnail_info": {"w": 256, "h": 245, "size": 216650, "mimetype": "image/png"}}, "msgtype": "m.sticker", "id": "tg-6060109721199706546", "net.maunium.telegram.sticker": {"pack": {"id": "4923007431547551745", "short_name": "gblpack"}, "id": "6060109721199706546", "emoticons": ["🤔"]}}, {"body": "🌻", "url": "mxc://matrix.org/umSlzuniVlYmrjkCpXjRZYlw", "info": {"w": 256, "h": 230, "size": 260475, "mimetype": "image/png", "thumbnail_url": "mxc://matrix.org/umSlzuniVlYmrjkCpXjRZYlw", "thumbnail_info": {"w": 256, "h": 230, "size": 260475, "mimetype": "image/png"}}, "msgtype": "m.sticker", "id": "tg-6134429006361002861", "net.maunium.telegram.sticker": {"pack": {"id": "4923007431547551745", "short_name": "gblpack"}, "id": "6134429006361002861", "emoticons": ["🌻"]}}, {"body": "😅", "url": "mxc://matrix.org/iqYBJLwiSQAhlpAjfLfcEraL", "info": {"w": 256, "h": 256, "size": 186301, "mimetype": "image/png", "thumbnail_url": "mxc://matrix.org/iqYBJLwiSQAhlpAjfLfcEraL", "thumbnail_info": {"w": 256, "h": 256, "size": 186301, "mimetype": "image/png"}}, "msgtype": "m.sticker", "id": "tg-6134442170435764744", "net.maunium.telegram.sticker": {"pack": {"id": "4923007431547551745", "short_name": "gblpack"}, "id": "6134442170435764744", "emoticons": ["😅"]}}, {"body": "🤔", "url": "mxc://matrix.org/WOLEQIqloVJlKYfVgwsKzEep", "info": {"w": 256, "h": 144, "size": 279167, "mimetype": "image/png", "thumbnail_url": "mxc://matrix.org/WOLEQIqloVJlKYfVgwsKzEep", "thumbnail_info": {"w": 256, "h": 144, "size": 279167, "mimetype": "image/png"}}, "msgtype": "m.sticker", "id": "tg-6160947899678064960", "net.maunium.telegram.sticker": {"pack": {"id": "4923007431547551745", "short_name": "gblpack"}, "id": "6160947899678064960", "emoticons": ["🤔"]}}, {"body": "🤨", "url": "mxc://matrix.org/gUqZITEBzHGemiEmrenxUdmq", "info": {"w": 256, "h": 185, "size": 120770, "mimetype": "image/png", "thumbnail_url": "mxc://matrix.org/gUqZITEBzHGemiEmrenxUdmq", "thumbnail_info": {"w": 256, "h": 185, "size": 120770, "mimetype": "image/png"}}, "msgtype": "m.sticker", "id": "tg-6147865523783730046", "net.maunium.telegram.sticker": {"pack": {"id": "4923007431547551745", "short_name": "gblpack"}, "id": "6147865523783730046", "emoticons": ["🤨"]}}]}